scaffoldPandas.py
scaffoldpandas-0.17.dist-info/LICENSE
scaffoldpandas-0.17.dist-info/WHEEL
scaffoldpandas-0.17.dist-info/METADATA
scaffoldpandas-0.17.dist-info/RECORD
